{"id":"cc7638","long_description":{},"name":{"CC":"高​等​法​院​法​官 第​80​辦​公​處","EN":"JUDGE OF THE SUPERIOR COURT Office No. 80","ES":"JUEZ DE LA CORTE SUPERIOR Cargo N.° 80","FA":"قاضی دادگاه عالی شماره دفتر 80","HI":"उच्च न्यायालय के न्यायाधीश कार्यालय सं. 80","HY":"ՎԵՐԱԴԱՍ ԴԱՏԱՐԱՆԻ ԴԱՏԱՎՈՐ Գրասենյակ Համար 80","JA":"上​位​裁​判​所​裁​判​官 公​職​番​号 80","KM":"ចៅ​ក្រម​តុលាការ​ជាន់​ខ្ពស់ ការិយាល័យ​លេ​ខ 80","KO":"상급 법원 판사 공직 번호 80","RU":"СУДЬЯ ВЫСШЕГО СУДА, ДОЛЖНОСТЬ № 80","TH":"ผู้​พิพากษา​ศาล​สูง ตำแหน่ง​หมายเลข 80","TL":"HUKOM NG HUKUMANG SUPERYOR Opisina Blg. 80","VI":"THẨM PHÁN TÒA THƯỢNG THẨM Văn Phòng Số 80","ZH":"高​等​法​院​法​官 第​80​辦​公​處"},"short_name":{"CC":"高​等​法​院​法​官 #​80","EN":"JUDGE-SUPERIOR COURT #80","ES":"JUEZ - CORTE SUPERIOR N.° 80","FA":"قاضی-دادگاه عالی شماره 80","HI":"न्यायाधीश-वरिष्ठ न्यायालय #80","HY":"Համար 80 ՎԵՐԻՆ ԴԱՏԱՐԱՆԻ ԴԱՏԱՎՈՐ","JA":"裁​判​官​-​上​裁​#​80","KM":"ចៅ​ក្រម​-​តុលាការ​ជាន់​ខ្ពស់ #​80","KO":"상급법원 판사 #80","RU":"СУДЬЯ ВЫСШЕГО СУДА № 80","TH":"ผู้​พิพากษา​-​ศาล​สูง #​80","TL":"HUKOM-HUKUMANG SUPERYOR #80","VI":"THẨM PHÁN TÒA THƯỢNG THẨM 80","ZH":"高​等​法​院​法​官 #​80"},"short_description":{},"contest_class":"candidate_class","number_of_writeins":1,"vote_for_max":1,"vote_for_text":{"CC":"請​選 ​​<b>​一​人​​</b>​","EN":"Vote For ​<b>​ONE​</b>​","ES":"Vote Por ​<b>​UNO​</b>​","FA":"رای به ​<b>​یک نفر​</b>​  ","HI":"​<b>​एक​</b>​ के लिए मतदान करें","HY":"Քվեարկեք ​<b>​ՄԵԿԻ ​</b>​Համար","JA":" ​​<b>​一​人​​</b>​に​投​票","KM":"បោះឆ្នោត​អោ​យ <b>​មួយ​</b>","KO":"​<b>​한​</b>​ 명까지만 투표하십시오","RU":"Голосовать за ​<b>​ОДНОГО​</b>​ кандидата","TH":"ออกเสียง​ลงคะแนน​เลือก​เพียง <b>​หนึ่ง​</b>  ชื่อ ","TL":"Bumoto Ng ​<b>​ISA​</b>​","VI":"Bầu ​<b>​MỘT​</b>​ Người","ZH":"請​選 ​​<b>​一​人​​</b>​"},"division":"D63","candidates":[{"id":"3FA","name":[{"CC":"大​衛·A.·貝​格​爾","EN":"DAVID A. BERGER","FA":"دیوید آ. برگر","HI":"डेविड ए. बर्जर","HY":"ԴԵՅՎԻԴ Ա. ԲԵՌԳԵՌ","JA":"デ​ビッ​ド・​A.・​バー​ガー","KM":"ដេវីដ អេ ប៊ើ​ជើ​រ","KO":"데이비드 A. 버거","RU":"ДЭВИД А. БЕРГЕР","TH":"เด​วิด เอ. เบอร์​เจอ​ร์","ZH":"大​衛·A.·貝​格​爾"}],"short_name":[{"EN":"DAVID A BERGER"}],"occupation":[{"CC":"Los Angeles​縣​地​區​助​理​檢​察​官","EN":"Deputy District Attorney, County of Los Angeles","ES":"Fiscal de Distrito Adjunto, Condado de Los Angeles","FA":"معاون بازپرس بخش قضایی، شهرستان Los Angeles","HI":"ज़िला सहायक वकील, Los Angeles काउंटी","HY":"Շրջանային դատախազի տեղակալ, Los Angeles վարչաշրջան","JA":"地​方​検​事​副​官、​Los Angeles 郡","KM":"មេធាវី​មណ្ឌល​រង, ខោ​ន​ធី Los Angeles","KO":"Los Angeles 카운티 지방 검사 대리인","RU":"Заместитель районного прокурора округа Los Angeles","TH":"รอง​อัยการ​เขต, มณฑล Los Angeles","TL":"Kinatawang Abugado ng Distrito, County ng Los Angeles","VI":"Phó Biện Lý Khu, Quận Los Angeles","ZH":"Los Angeles​縣​地​區​助​理​檢​察​官"}],"statements":[],"order":0,"isWriteIn":false},{"id":"3FB","name":[{"CC":"克​林​特·詹​姆​斯·麥​凱","EN":"KLINT JAMES MCKAY","FA":"کلینت جیمز مکی","HI":"क्लिंट जेम्स मैके","HY":"ՔԼԻՆԹ ՋԵՅՄՍ ՄԱԿՔԵՅ","JA":"ク​リ​ン​ト・​ジェー​ム​ズ・​マッ​ケ​イ","KM":"ឃ្លី​ន ជែ​ម​ស៍ ម៉ក់​ខេ​យ៍","KO":"클린트 제임스 맥케이","RU":"КЛИНТ ДЖЕЙМС МАККЕЙ","TH":"ค​ลิ​นท์ เจ​มส์ แมค​เคย​์","ZH":"克​林​特·詹​姆​斯·麥​凱"}],"short_name":[{"EN":"KLINT JAMES MCKAY"}],"occupation":[{"CC":"California​州​社​會​服​務​部​行​政​法​法​官","EN":"Administrative Law Judge, California Department of Social Services","ES":"Juez de Derecho Administrativo, Departamento de Servicios Sociales de California","FA":"قاضی قانون اداری، اداره خدمات اجتماعی California","HI":"प्रशासनिक विधि न्यायाधीश, कैलिफोर्निया का सामाजिक सेवा विभाग","HY":"Վարչական իրավունքի դատավոր, California-ի Սոցիալական ծառայությունների բաժանմունք","JA":"行​政​法​審​判​官、​California​社​会​サー​ビ​ス​部​門","KM":"ចៅក្រម​ច្បាប់​រដ្ឋបាល, ក្រសួង​សេវា​ស​ង្គម​កិច្ច​រដ្ឋ California","KO":"California 사회서비스 부서 행정법 판사","RU":"Судья по административным делам в департаменте социального обслуживания штата California","TH":"ผู้​พิพากษา​กฎหมาย​ปก​ครอง, ฝ่าย​บริการ​ด้าน​สังคม​รัฐ California","TL":"Hukom ng Batas Pampangasiwaan, Departamento ng mga Serbisyong Panlipunan ng California","VI":"Thẩm Phán Luật Hành Chánh, Phòng Dịch Vụ Xã Hội California","ZH":"California​州​社​會​服​務​部​行​政​法​法​官"}],"statements":[],"order":1,"isWriteIn":false},{"id":"3SJ","name":[{"CC":"自​填​候​選​人","EN":"Write-In Candidate","ES":"Candidato por Escrito","FA":"کاندیدا خارج از لیست","HI":"राइट–इन उम्मीदवार","HY":"Գրավոր առաջադրված թեկնածու","JA":"記​入​候​補​者","KM":"បេក្ខជន​ស​រសេ​រប​ញ្ចូល​ឈ្មោះ","KO":"기명 후보자","RU":"Вписанный кандидат","TH":"ผู้​สมัคร​รับ​เลือกตั้ง​แบบ​เขียน​ชื่อ","TL":"Isinusulat-lamang na Kandidato","VI":"Ứng Cử Viên Viết Tên Vào","ZH":"自​填​候​選​人"}],"short_name":[{"EN":"Write-In Candidate"}],"occupation":[null],"statements":[],"order":3,"isWriteIn":true}],"statements":[]}